mosaic/__init__.py
mosaic/__meta__.py
mosaic/test.py
mosaic_libraries-0.1.0.dist-info/METADATA
mosaic_libraries-0.1.0.dist-info/WHEEL
mosaic_libraries-0.1.0.dist-info/top_level.txt
mosaic_libraries-0.1.0.dist-info/RECORD
